cactus_client/__init__.py
cactus_client/constants.py
cactus_client/error.py
cactus_client/py.typed
cactus_client/sep2.py
cactus_client/time.py
cactus_client/action/__init__.py
cactus_client/action/der.py
cactus_client/action/der_controls.py
cactus_client/action/discovery.py
cactus_client/action/end_device.py
cactus_client/action/mup.py
cactus_client/action/noop.py
cactus_client/action/notifications.py
cactus_client/action/refresh_resource.py
cactus_client/action/server.py
cactus_client/action/subscription.py
cactus_client/action/wait.py
cactus_client/check/__init__.py
cactus_client/check/der.py
cactus_client/check/der_controls.py
cactus_client/check/discovered.py
cactus_client/check/end_device.py
cactus_client/check/function_set_assignment.py
cactus_client/check/mup.py
cactus_client/check/sep2.py
cactus_client/check/time.py
cactus_client/cli/__init__.py
cactus_client/cli/client.py
cactus_client/cli/common.py
cactus_client/cli/main.py
cactus_client/cli/run.py
cactus_client/cli/server.py
cactus_client/cli/setup.py
cactus_client/cli/tests.py
cactus_client/execution/__init__.py
cactus_client/execution/build.py
cactus_client/execution/execute.py
cactus_client/execution/keypress.py
cactus_client/execution/run.py
cactus_client/execution/tui.py
cactus_client/model/__init__.py
cactus_client/model/config.py
cactus_client/model/context.py
cactus_client/model/execution.py
cactus_client/model/http.py
cactus_client/model/output.py
cactus_client/model/parameter.py
cactus_client/model/progress.py
cactus_client/model/resource.py
cactus_client/results/__init__.py
cactus_client/results/common.py
cactus_client/results/console.py
cactus_client/results/requests.py
cactus_client/schema/__init__.py
cactus_client/schema/validator.py
cactus_client/schema/csipaus12/__init__.py
cactus_client/schema/csipaus12/csipaus-core.xsd
cactus_client/schema/csipaus12/csipaus-ext.xsd
cactus_client/schema/csipaus12/sep.xsd
cactus_client-0.0.11.dist-info/licenses/LICENSE
cactus_client-0.0.11.dist-info/METADATA
cactus_client-0.0.11.dist-info/WHEEL
cactus_client-0.0.11.dist-info/entry_points.txt
cactus_client-0.0.11.dist-info/top_level.txt
cactus_client-0.0.11.dist-info/RECORD
